.coveragerc
AUTHORS
ChangeLog
LICENSE.txt
README.md
requirements.txt
setup.cfg
setup.py
.github/workflows/ci.yml
clang_build/__init__.py
clang_build/build_type.py
clang_build/circle.py
clang_build/cli.py
clang_build/directories.py
clang_build/environment.py
clang_build/errors.py
clang_build/flags.py
clang_build/git_tools.py
clang_build/io_tools.py
clang_build/logging_tools.py
clang_build/progress_bar.py
clang_build/project.py
clang_build/single_source.py
clang_build/target.py
clang_build/toolchain.py
clang_build/tree_entry.py
clang_build.egg-info/PKG-INFO
clang_build.egg-info/SOURCES.txt
clang_build.egg-info/dependency_links.txt
clang_build.egg-info/entry_points.txt
clang_build.egg-info/not-zip-safe
clang_build.egg-info/pbr.json
clang_build.egg-info/requires.txt
clang_build.egg-info/top_level.txt
docs/.gitignore
docs/Makefile
docs/conf.py
docs/index.rst
docs/make.bat
docs/code_documentation/code_documentation.rst
docs/user_guide/bundling.rst
docs/user_guide/customisations.rst
docs/user_guide/defaults.rst
docs/user_guide/first_steps.rst
docs/user_guide/inheritance.rst
docs/user_guide/multiple_projects.rst
docs/user_guide/multiple_targets.rst
docs/user_guide/platform_dependence.rst
docs/user_guide/scripting.rst
docs/user_guide/user_guide.rst
test/__init__.py
test/test.py
test/boost-filesystem/clang-build.toml
test/boost-filesystem/main.cpp
test/boost-filesystem/boost_dependencies/clang-build.toml
test/build_errors/compile_error/hello.cpp
test/build_errors/link_error/clang-build.toml
test/build_errors/link_error/hello.cpp
test/c-library/clang-build.toml
test/c-library/main.cpp
test/c-library/qhull/clang-build.toml
test/configuration_errors/__init__.py
test/configuration_errors/test.py
test/configuration_errors/circular_dependency/clang-build.toml
test/configuration_errors/circular_dependency/src/empty.cpp
test/configuration_errors/missing_name_with_subproject/clang-build.toml
test/configuration_errors/missing_subproject_name/clang-build.toml
test/configuration_errors/missing_subproject_name/sub/clang-build.toml
test/configuration_errors/missing_subproject_toml/clang-build.toml
test/multi_target_external/clang-build.toml
test/multi_target_external/myexe/main.cpp
test/multi_target_external/mylib/include/DLL_Define_Export.h
