Metadata-Version: 2.1
Name: clang-build
Version: 0.0.0
Summary: Easy build tool for C++ projects focussing on simplicity
Home-page: https://github.com/Trick-17/clang-build
Author: Trick-17
License: MIT
Keywords: clang,build
Platform: UNKNOWN
Requires-Python: >=3.7
